apimagic/__init__.py
apimagic/jtools1.py
apimagic/jtools2.py
apimagic/magic.py
apimagic-0.0.2.dist-info/LICENSE
apimagic-0.0.2.dist-info/METADATA
apimagic-0.0.2.dist-info/WHEEL
apimagic-0.0.2.dist-info/top_level.txt
apimagic-0.0.2.dist-info/RECORD
